{
  "articles": [
    {
      "id": "0191dcf9fb-516b-75d5-a71f-edab5a1bc5db",
      "video": "/c0WPKwFh1 - Porn Videos   Photos - EroMe.mp4",
      "title": "Big butt gracie bon gets her ass fucked",
      "creators": ["Gracie Bon"],
      "tags": ["Big Butts", "Phat ass", "Latin", "Bbw", "Sexy", "Hardcore"],
      "description": "Big butt gracie bon getting fucked sideways"
    },
    {
      "id": "0192ab0ac8-0567-7119-9410-19d0ba1a3260",
      "video": "/Big booty grinds bbc on couch - Porn Videos   Photos - EroMe.mp4",
      "title": "Big booty grinds bbc on couch",
      "creators": ["Unavailable"],
      "tags": ["Big Booty", "Big Butts", "Bbc", "Latin"],
      "description": "Big booty grinds bbc on couch"
    },
    {
      "id": "019101f9fb-516b-75d5-a71f-edab5a1nf4365db",
      "video": "/ebony phat ass fucked by big cock - XVIDEOS.COM.mp4",
      "title": "Ebony phat ass fucked by big cock",
      "creators": ["Unavailable"],
      "tags": ["Big Butts", "Phat ass", "Bbc", "Ebony", "Bbw"],
      "description": "ebony phat ass fucked by big cock"
    },
    {
      "id": "0192020ac8-0567-7119-9410-19d0b3j63260",
      "video": "/Phatty adventure s - Porn Videos   Photos - EroMe.mp4",
      "title": "Phat ass ebony fucked",
      "creators": ["Lala koi"],
      "tags": ["Big Butts", "Phat ass", "Bbc", "Ebony"],
      "description": "Phatty adventure s, Phat ass ebony fucked"
    },
    {
      "id": "0192020ac8-0567-7119-9410-19d0b3j6ams1082",
      "video": "/That’s a WET and really WILD ride! (LOUD MOANING) - EroMe.mp4",
      "title": "That’s a WET and really WILD ride! (LOUD MOANING)",
      "creators": ["Muva Phoenix"],
      "tags": ["Big Butts", "Phat ass", "Bbc", "Ebony", "Bbw", "Big Booty"],
      "description": "That’s a WET and really WILD ride! (LOUD MOANING)"
    },
    {
      "id": "0191092cvc8-0567-7119-9410-19d0b3j63260",
      "video": "/thejuliecash 3 - Porn Videos   Photos - EroMe.mp4",
      "title": "Big butt girl blow job",
      "creators": ["Julie Cash"],
      "tags": ["Big Butts", "Phat ass", "Blow Job"],
      "description": "Big butt girl blow job, Julie cash"
    },
    {
      "id": "01910922bz9-2871-2014-baz0-19d0d9bg3260",
      "video": "/sethi - Vidéos porno et photos - EroMe.mp4",
      "title": "Ms sethi riding lucky guy",
      "creators": ["Ms Sethi"],
      "tags": ["Big Butts", "Phat ass", "Pawg", "Thick ass"],
      "description": "Ms sethi riding lucky guy"
    },
    {
      "id": "019109007z9-0091-0987-zp20-19d0d9bg3260",
      "video": "/Only Fans 2024 Graciebon Couch Sextape XXX 1080p MP4-P2Pž • Pornhex.mp4",
      "title": "2024 Graciebon Couch Sextape",
      "creators": ["Gracie Bon"],
      "tags": ["Big Butts", "Phat ass", "Pawg", "Thick ass", "Riding"],
      "description": "2024 Graciebon Couch Sextape"
    },
    {
      "id": "01910920mn8-2091-0814-abc0-19d0c6bg3260",
      "video": "/POUNDTOWN - Porn Videos   Photos - EroMe.mp4",
      "title": "Big butt fucked doggy style",
      "creators": ["Ms Sethi"],
      "tags": ["Big Butts", "Phat ass", "Pawg", "Doggy"],
      "description": "Big butt fucked doggy style, Ms Sethi doggy style"
    },
    {
      "id": "01910920mn8-0567-7119-abc0-19d0b6rj3260",
      "video": "/Graciebon - Olyfans • Pornhex.mp4",
      "title": "Gracie Bon riding in car",
      "creators": ["Gracie Bon"],
      "tags": ["Big Butts", "Phat ass", "Blow Job", "Riding"],
      "description": "Gracie Bon riding in car, Graciebon - Onlyfans"
    }
  ]
}
